best/__init__.py
best/integration/__init__.py
best/unit/__init__.py
best/unit/conftest.py
best/unit/test_glue_session.py
best/unit/test_glue_session_demo.py
best/unit/test_session_apis.py
ec2_hibinit_agent-119.4.6.dist-info/LICENSE.txt
ec2_hibinit_agent-119.4.6.dist-info/METADATA
ec2_hibinit_agent-119.4.6.dist-info/WHEEL
ec2_hibinit_agent-119.4.6.dist-info/top_level.txt
ec2_hibinit_agent-119.4.6.dist-info/RECORD
